hfsslib/constants.py
hfsslib/hfss.py
hfsslib/hfss_writer.py
hfsslib/__init__.py
hfsslib-0.0.0.dist-info/DESCRIPTION.rst
hfsslib-0.0.0.dist-info/METADATA
hfsslib-0.0.0.dist-info/metadata.json
hfsslib-0.0.0.dist-info/RECORD
hfsslib-0.0.0.dist-info/top_level.txt
hfsslib-0.0.0.dist-info/WHEEL
