Metadata-Version: 2.0
Name: hfsslib
Version: 0.0.0
Summary: A toolset for working with HFSS files
Home-page: http://git.arrc.ou.edu/pier3595/hfss-lib
Author: Cody Piersall
Author-email: codypi@ou.edu
License: UNKNOWN
Platform: UNKNOWN
Classifier: Intended Audience :: Developers
Classifier: Topic :: Scientific/Engineering
Classifier: Programming Language :: Python :: 2
Classifier: Programming Language :: Python :: 2.7
Classifier: Programming Language :: Python :: 3
Classifier: Programming Language :: Python :: 3.4
